pandes/__init__.py
pandes/runner.py
pandes/programs/__init__.py
pandes/programs/prog1.py
pandes/programs/prog2.py
pandes/programs/prog3.py
pandes/programs/prog4.py
pandes/programs/prog5.py
pandes/programs/prog6.py
pandes/programs/prog7.py
pandes/programs/prog8.py
pandes/programs/prog9.py
pandes-1.0.0.dist-info/METADATA
pandes-1.0.0.dist-info/WHEEL
pandes-1.0.0.dist-info/top_level.txt
pandes-1.0.0.dist-info/RECORD
