Metadata-Version: 2.1
Name: pandes
Version: 1.0.0
Summary: ML Lab Programs Runner
Author: Your Name
